daysgrounded/appinfo.py
daysgrounded/AUTHORS.txt
daysgrounded/ChangeLog.txt
daysgrounded/cli.py
daysgrounded/common.py
daysgrounded/daysgrounded.py
daysgrounded/gui_tk_func.py
daysgrounded/LICENSE.txt
daysgrounded/localization.py
daysgrounded/README.txt
daysgrounded/shared.py
daysgrounded/usage.txt
daysgrounded/usage_pt.txt
daysgrounded/__init__.py
daysgrounded/doc/.buildinfo
daysgrounded/doc/authors.html
daysgrounded/doc/changelog.html
daysgrounded/doc/daysgrounded.pdf
daysgrounded/doc/genindex.html
daysgrounded/doc/index.html
daysgrounded/doc/license.html
daysgrounded/doc/objects.inv
daysgrounded/doc/py-modindex.html
daysgrounded/doc/readme.html
daysgrounded/doc/reference.html
daysgrounded/doc/search.html
daysgrounded/doc/searchindex.js
daysgrounded/doc/_modules/cli.html
daysgrounded/doc/_modules/common.html
daysgrounded/doc/_modules/daysgrounded.html
daysgrounded/doc/_modules/gui_tk_func.html
daysgrounded/doc/_modules/index.html
daysgrounded/doc/_modules/localization.html
daysgrounded/doc/_modules/shared.html
daysgrounded/doc/_sources/authors.txt
daysgrounded/doc/_sources/changelog.txt
daysgrounded/doc/_sources/index.txt
daysgrounded/doc/_sources/license.txt
daysgrounded/doc/_sources/readme.txt
daysgrounded/doc/_sources/reference.txt
daysgrounded/doc/_static/ajax-loader.gif
daysgrounded/doc/_static/alabaster.css
daysgrounded/doc/_static/basic.css
daysgrounded/doc/_static/comment-bright.png
daysgrounded/doc/_static/comment-close.png
daysgrounded/doc/_static/comment.png
daysgrounded/doc/_static/doctools.js
daysgrounded/doc/_static/down-pressed.png
daysgrounded/doc/_static/down.png
daysgrounded/doc/_static/file.png
daysgrounded/doc/_static/jquery-1.11.1.js
daysgrounded/doc/_static/jquery.js
daysgrounded/doc/_static/minus.png
daysgrounded/doc/_static/plus.png
daysgrounded/doc/_static/pygments.css
daysgrounded/doc/_static/searchtools.js
daysgrounded/doc/_static/underscore-1.3.1.js
daysgrounded-0.0.34.dist-info/DESCRIPTION.rst
daysgrounded-0.0.34.dist-info/entry_points.txt
daysgrounded-0.0.34.dist-info/METADATA
daysgrounded-0.0.34.dist-info/metadata.json
daysgrounded-0.0.34.dist-info/RECORD
daysgrounded-0.0.34.dist-info/top_level.txt
daysgrounded-0.0.34.dist-info/WHEEL
