Metadata-Version: 2.0
Name: daysgrounded
Version: 0.0.34
Summary: Allows you to manage your kid's grounded days (simple app for trying Python programming and testing procedures).
Home-page: https://github.com/jcrmatos/daysgrounded
Author: Joao Carlos Roseta Matos
Author-email: jcrmatos@gmail.com
License: GNU General Public License v2 or later (GPLv2+)
Keywords: d,a,y,s, ,g,r,o,u,n,d,e,d
Platform: UNKNOWN
Classifier: Development Status :: 5 - Production/Stable
Classifier: Environment :: Console
Classifier: Environment :: MacOS X
Classifier: Environment :: Other Environment
Classifier: Environment :: Win32 (MS Windows)
Classifier: Environment :: X11 Applications
Classifier: Intended Audience :: End Users/Desktop
Classifier: License :: OSI Approved :: GNU General Public License v2 or later (GPLv2+)
Classifier: Natural Language :: English
Classifier: Natural Language :: Portuguese
Classifier: Operating System :: OS Independent
Classifier: Programming Language :: Python
Classifier: Programming Language :: Python :: 2
Classifier: Programming Language :: Python :: 2.7
Classifier: Programming Language :: Python :: 3
Classifier: Programming Language :: Python :: 3.4
Classifier: Topic :: Other/Nonlisted Topic
Requires-Dist: colorama
Requires-Dist: future
